rtl/gpio/gpio_top.sv
// GPIO Controller
// 16-bit bidirectional general purpose I/O
// Each pin can be configured as input or output

module gpio_top (
  input  logic        clk_i,
  input  logic        rst_ni,

  // TL-UL Bus Interface
  input  logic        we_i,
  input  logic [31:0] wdata_i,
  input  logic [3:0]  addr_i,
  output logic [31:0] rdata_o,

  // GPIO pins
  input  logic [15:0] gpio_in_i,
  output logic [15:0] gpio_out_o,
  output logic [15:0] gpio_oe_o
);

  // Register addresses
  localparam ADDR_DATA_OUT = 4'h0;
  localparam ADDR_DATA_IN  = 4'h4;
  localparam ADDR_OE       = 4'h8;

  // Registers
  logic [15:0] data_out_reg;
  logic [15:0] oe_reg;

  // Write
  always_ff @(posedge clk_i or negedge rst_ni) begin
    if (!rst_ni) begin
      data_out_reg <= 16'h0;
      oe_reg       <= 16'h0;
    end else begin
      if (we_i) begin
        case (addr_i)
          ADDR_DATA_OUT: data_out_reg <= wdata_i[15:0];
          ADDR_OE:       oe_reg       <= wdata_i[15:0];
          default: ;
        endcase
      end
    end
  end

  // Read
  always_comb begin
    rdata_o = 32'h0;
    case (addr_i)
      ADDR_DATA_OUT: rdata_o = {16'h0, data_out_reg};
      ADDR_DATA_IN:  rdata_o = {16'h0, gpio_in_i};
      ADDR_OE:       rdata_o = {16'h0, oe_reg};
      default:       rdata_o = 32'h0;
    endcase
  end

  assign gpio_out_o = data_out_reg;
  assign gpio_oe_o  = oe_reg;

endmodule

gpio_wave.vcd
$version Generated by VerilatedVcd $end
$timescale 1ps $end
 $scope module TOP $end
  $var wire 1 # clk_i $end
  $var wire 1 $ rst_ni $end
  $var wire 1 % we_i $end
  $var wire 32 & wdata_i [31:0] $end
  $var wire 4 ' addr_i [3:0] $end
  $var wire 32 ( rdata_o [31:0] $end
  $var wire 16 ) gpio_in_i [15:0] $end
  $var wire 16 * gpio_out_o [15:0] $end
  $var wire 16 + gpio_oe_o [15:0] $end
  $scope module gpio_top $end
   $var wire 1 # clk_i $end
   $var wire 1 $ rst_ni $end
   $var wire 1 % we_i $end
   $var wire 32 & wdata_i [31:0] $end
   $var wire 4 ' addr_i [3:0] $end
   $var wire 32 ( rdata_o [31:0] $end
   $var wire 16 ) gpio_in_i [15:0] $end
   $var wire 16 * gpio_out_o [15:0] $end
   $var wire 16 + gpio_oe_o [15:0] $end
   $var wire 4 . ADDR_DATA_OUT [3:0] $end
   $var wire 4 / ADDR_DATA_IN [3:0] $end
   $var wire 4 0 ADDR_OE [3:0] $end
   $var wire 16 , data_out_reg [15:0] $end
   $var wire 16 - oe_reg [15:0] $end
  $upscope $end
 $upscope $end
$enddefinitions $end


#0
0#
0$
0%
b00000000000000000000000000000000 &
b0000 '
b00000000000000000000000000000000 (
b0000000000000000 )
b0000000000000000 *
b0000000000000000 +
b0000000000000000 ,
b0000000000000000 -
b0000 .
b0100 /
b1000 0
#1
1#
#2
0#
#3
1#
#4
0#
#5
1#
#6
0#
#7
1#
#8
0#
#9
1#
#10
0#
1$
#11
1#
#12
0#
1%
b00000000000000001111111111111111 &
b1000 '
#13
1#
b00000000000000001111111111111111 (
b1111111111111111 +
b1111111111111111 -
#14
0#
0%
#15
1#
#16
0#
1%
b00000000000000001010101111001101 &
b0000 '
b00000000000000000000000000000000 (
#17
1#
b00000000000000001010101111001101 (
b1010101111001101 *
b1010101111001101 ,
#18
0#
0%
#19
1#
#20
0#
b0001001000110100 )
#21
1#
#22
0#
b0100 '
b00000000000000000001001000110100 (
#23
1#
#24
0#
1%
b00000000000000000000000011111111 &
b1000 '
b00000000000000001111111111111111 (
#25
1#
b00000000000000000000000011111111 (
b0000000011111111 +
b0000000011111111 -
#26
0#
b00000000000000000000000001010101 &
b0000 '
b00000000000000001010101111001101 (
#27
1#
b00000000000000000000000001010101 (
b0000000001010101 *
b0000000001010101 ,
#28
0#
0%
