rtl/sram_ecc/ecc_encode.sv
// SEC-DED ECC Encoder
// Generates 7 parity check bits for 32-bit data
// Uses Hamming(39,32) code

module ecc_encode (
  input  logic [31:0] data_i,
  output logic [6:0]  ecc_o
);

  // Parity bits P1-P6 + overall parity P7
  // Bit positions in Hamming code (1-indexed):
  // P1=1, P2=2, P3=4, P4=8, P5=16, P6=32, P7=overall

  logic p1, p2, p3, p4, p5, p6, p7;

  // P1 covers bits at positions with bit0=1: 1,3,5,7,9,11...
  assign p1 = data_i[0]  ^ data_i[1]  ^ data_i[3]  ^ data_i[4]  ^
              data_i[6]  ^ data_i[8]  ^ data_i[10] ^ data_i[11] ^
              data_i[13] ^ data_i[15] ^ data_i[17] ^ data_i[19] ^
              data_i[21] ^ data_i[23] ^ data_i[25] ^ data_i[26] ^
              data_i[28] ^ data_i[30];

  // P2 covers bits at positions with bit1=1: 2,3,6,7,10,11...
  assign p2 = data_i[0]  ^ data_i[2]  ^ data_i[3]  ^ data_i[5]  ^
              data_i[6]  ^ data_i[9]  ^ data_i[10] ^ data_i[12] ^
              data_i[13] ^ data_i[16] ^ data_i[17] ^ data_i[20] ^
              data_i[21] ^ data_i[24] ^ data_i[25] ^ data_i[27] ^
              data_i[28] ^ data_i[31];

  // P3 covers bits at positions with bit2=1: 4,5,6,7,12,13...
  assign p3 = data_i[1]  ^ data_i[2]  ^ data_i[3]  ^ data_i[7]  ^
              data_i[8]  ^ data_i[9]  ^ data_i[10] ^ data_i[14] ^
              data_i[15] ^ data_i[16] ^ data_i[17] ^ data_i[22] ^
              data_i[23] ^ data_i[24] ^ data_i[25] ^ data_i[29] ^
              data_i[30] ^ data_i[31];

  // P4 covers bits at positions with bit3=1: 8-15, 24-31
  assign p4 = data_i[4]  ^ data_i[5]  ^ data_i[6]  ^ data_i[7]  ^
              data_i[8]  ^ data_i[9]  ^ data_i[10] ^ data_i[18] ^
              data_i[19] ^ data_i[20] ^ data_i[21] ^ data_i[22] ^
              data_i[23] ^ data_i[24] ^ data_i[25];

  // P5 covers bits at positions with bit4=1: 16-31
  assign p5 = data_i[11] ^ data_i[12] ^ data_i[13] ^ data_i[14] ^
              data_i[15] ^ data_i[16] ^ data_i[17] ^ data_i[18] ^
              data_i[19] ^ data_i[20] ^ data_i[21] ^ data_i[22] ^
              data_i[23] ^ data_i[24] ^ data_i[25];

  // P6 covers bits at positions with bit5=1: 32-63
  assign p6 = data_i[26] ^ data_i[27] ^ data_i[28] ^ data_i[29] ^
              data_i[30] ^ data_i[31];

  // P7 overall parity (for double error detection)
  assign p7 = ^data_i ^ p1 ^ p2 ^ p3 ^ p4 ^ p5 ^ p6;

  assign ecc_o = {p7, p6, p5, p4, p3, p2, p1};

endmodule

rtl/sram_ecc/ecc_decode.sv
// SEC-DED ECC Decoder
// Corrects single bit errors, detects double bit errors

module ecc_decode (
  input  logic [31:0] data_i,       // raw data from SRAM
  input  logic [6:0]  ecc_i,        // stored ECC bits
  output logic [31:0] data_o,       // corrected data
  output logic        single_err_o, // single error corrected
  output logic        double_err_o  // double error detected
);

  logic [6:0]  ecc_recalc;  // recalculated ECC
  logic [5:0]  syndrome;    // error syndrome (which bit is wrong)
  logic        overall_p;   // overall parity check

  // Recalculate ECC from received data
  ecc_encode u_ecc_recheck (
    .data_i (data_i),
    .ecc_o  (ecc_recalc)
  );

  // Syndrome = recalculated ECC XOR stored ECC (bits 5:0 only)
  assign syndrome  = ecc_recalc[5:0] ^ ecc_i[5:0];

  // Overall parity check
  assign overall_p = ^data_i ^ ^ecc_i;

  // Error detection and correction
  always_comb begin
    data_o       = data_i;
    single_err_o = 1'b0;
    double_err_o = 1'b0;

    if (syndrome == 6'h0 && overall_p == 1'b0) begin
      // No error
      data_o       = data_i;
      single_err_o = 1'b0;
      double_err_o = 1'b0;

    end else if (syndrome != 6'h0 && overall_p == 1'b1) begin
      // Single bit error — correct it
      single_err_o    = 1'b1;
      data_o          = data_i;
      // Flip the erroneous bit
      if (syndrome <= 32)
        data_o[syndrome-1] = ~data_i[syndrome-1];

    end else begin
      // Double bit error — cannot correct
      data_o       = data_i;
      double_err_o = 1'b1;
    end
  end

endmodule

rtl/sram_ecc/sram_ecc_top.sv
// SRAM Controller with SEC-DED ECC
// - 32-bit data width
// - 256 depth (256 x 32-bit words)
// - SEC-DED ECC (Single Error Correct, Double Error Detect)
// - 7 check bits for 32-bit data (Hamming code)

module sram_ecc_top (
  input  logic        clk_i,
  input  logic        rst_ni,

  // TL-UL Bus Interface
  input  logic        we_i,
  input  logic [31:0] wdata_i,
  input  logic [7:0]  addr_i,
  output logic [31:0] rdata_o,

  // ECC status
  output logic        single_err_o,  // single bit error corrected
  output logic        double_err_o   // double bit error detected
);

  // Internal signals
  logic [6:0]  ecc_encode_out;   // 7 check bits
  logic [38:0] sram_wdata;       // 32 data + 7 ECC bits
  logic [38:0] sram_rdata;       // raw read data
  logic [31:0] corrected_data;   // corrected output
  logic        single_err;
  logic        double_err;

  // SRAM array (256 x 39 bits — 32 data + 7 ECC)
  logic [38:0] mem [0:255];

  // ── ECC Encode on Write ──
  ecc_encode u_ecc_encode (
    .data_i (wdata_i),
    .ecc_o  (ecc_encode_out)
  );

  assign sram_wdata = {ecc_encode_out, wdata_i};

  // ── SRAM Write ──
  always_ff @(posedge clk_i) begin
    if (we_i) begin
      mem[addr_i] <= sram_wdata;
    end
  end

  // ── SRAM Read ──
  always_ff @(posedge clk_i or negedge rst_ni) begin
    if (!rst_ni) begin
      sram_rdata <= 39'h0;
    end else begin
      sram_rdata <= mem[addr_i];
    end
  end

  // ── ECC Decode on Read ──
  ecc_decode u_ecc_decode (
    .data_i       (sram_rdata[31:0]),
    .ecc_i        (sram_rdata[38:32]),
    .data_o       (corrected_data),
    .single_err_o (single_err),
    .double_err_o (double_err)
  );

  // ── Output ──
  assign rdata_o      = corrected_data;
  assign single_err_o = single_err;
  assign double_err_o = double_err;

endmodule

sram_ecc_wave.vcd
$version Generated by VerilatedVcd $end
$timescale 1ps $end
 $scope module TOP $end
  $var wire 1 : clk_i $end
  $var wire 1 ; rst_ni $end
  $var wire 1 < we_i $end
  $var wire 32 = wdata_i [31:0] $end
  $var wire 8 > addr_i [7:0] $end
  $var wire 32 ? rdata_o [31:0] $end
  $var wire 1 @ single_err_o $end
  $var wire 1 A double_err_o $end
  $scope module sram_ecc_top $end
   $var wire 1 : clk_i $end
   $var wire 1 ; rst_ni $end
   $var wire 1 < we_i $end
   $var wire 32 = wdata_i [31:0] $end
   $var wire 8 > addr_i [7:0] $end
   $var wire 32 ? rdata_o [31:0] $end
   $var wire 1 @ single_err_o $end
   $var wire 1 A double_err_o $end
   $var wire 7 B ecc_encode_out [6:0] $end
   $var wire 39 C sram_wdata [38:0] $end
   $var wire 39 ) sram_rdata [38:0] $end
   $var wire 32 + corrected_data [31:0] $end
   $var wire 1 , single_err $end
   $var wire 1 - double_err $end
   $scope module u_ecc_decode $end
    $var wire 32 . data_i [31:0] $end
    $var wire 7 / ecc_i [6:0] $end
    $var wire 32 + data_o [31:0] $end
    $var wire 1 , single_err_o $end
    $var wire 1 - double_err_o $end
    $var wire 7 0 ecc_recalc [6:0] $end
    $var wire 6 1 syndrome [5:0] $end
    $var wire 1 2 overall_p $end
    $scope module u_ecc_recheck $end
     $var wire 32 . data_i [31:0] $end
     $var wire 7 0 ecc_o [6:0] $end
     $var wire 1 3 p1 $end
     $var wire 1 4 p2 $end
     $var wire 1 5 p3 $end
     $var wire 1 6 p4 $end
     $var wire 1 7 p5 $end
     $var wire 1 8 p6 $end
     $var wire 1 9 p7 $end
    $upscope $end
   $upscope $end
   $scope module u_ecc_encode $end
    $var wire 32 = data_i [31:0] $end
    $var wire 7 B ecc_o [6:0] $end
    $var wire 1 # p1 $end
    $var wire 1 $ p2 $end
    $var wire 1 % p3 $end
    $var wire 1 & p4 $end
    $var wire 1 ' p5 $end
    $var wire 1 ( p6 $end
    $var wire 1 E p7 $end
   $upscope $end
  $upscope $end
 $upscope $end
$enddefinitions $end


#0
0#
0$
0%
0&
0'
0(
b000000000000000000000000000000000000000 )
b00000000000000000000000000000000 +
0,
0-
b00000000000000000000000000000000 .
b0000000 /
b0000000 0
b000000 1
02
03
04
05
06
07
08
09
0:
0;
0<
b00000000000000000000000000000000 =
b00000000 >
b00000000000000000000000000000000 ?
0@
0A
b0000000 B
b000000000000000000000000000000000000000 C
0E
#1
1:
#2
0:
#3
1:
#4
0:
#5
1:
#6
0:
#7
1:
#8
0:
#9
1:
#10
0:
1;
#11
1:
#12
1#
1$
1(
0:
1<
b11011110101011011011111011101111 =
b1100011 B
b110001111011110101011011011111011101111 C
1E
#13
1:
#14
0:
0<
#15
b110001111011110101011011011111011101111 )
b11011110101011011011111011101111 +
b11011110101011011011111011101111 .
b1100011 /
b1100011 0
13
14
18
19
1:
b11011110101011011011111011101111 ?
#16
0:
#17
1:
#18
0$
1%
1&
0:
1<
b00010010001101000101011001111000 =
b00000001 >
b1101101 B
b110110100010010001101000101011001111000 C
#19
b000000000000000000000000000000000000000 )
b00000000000000000000000000000000 +
b00000000000000000000000000000000 .
b0000000 /
b0000000 0
03
04
08
09
1:
b00000000000000000000000000000000 ?
#20
1$
0%
1'
0:
b10101011110011011110111100000001 =
b00000010 >
b1111011 B
b111101110101011110011011110111100000001 C
#21
1:
#22
0$
0&
0:
b01010101101010100101010110101010 =
b00000011 >
b1110001 B
b111000101010101101010100101010110101010 C
#23
1:
#24
0:
0<
b00000001 >
#25
b110110100010010001101000101011001111000 )
b00010010001101000101011001111000 +
b00010010001101000101011001111000 .
b1101101 /
b1101101 0
13
15
16
18
19
1:
b00010010001101000101011001111000 ?
#26
0:
#27
1:
#28
0:
b00000010 >
#29
b111101110101011110011011110111100000001 )
b10101011110011011110111100000001 +
b10101011110011011110111100000001 .
b1111011 /
b1111011 0
14
05
17
1:
b10101011110011011110111100000001 ?
#30
0:
#31
1:
#32
0:
b00000011 >
#33
b111000101010101101010100101010110101010 )
b01010101101010100101010110101010 +
b01010101101010100101010110101010 .
b1110001 /
b1110001 0
04
06
1:
b01010101101010100101010110101010 ?
#34
0:
#35
1:
#36
0:
b00000000 >
#37
b110001111011110101011011011111011101111 )
b11011110101011011011111011101111 +
b11011110101011011011111011101111 .
b1100011 /
b1100011 0
14
07
1:
b11011110101011011011111011101111 ?
