rtl/timer/timer_top.sv
// 32-bit Hardware Timer
// Features:
// - 32-bit up counter
// - Configurable compare value
// - Interrupt on match
// - Start/stop control

module timer_top (
  input  logic        clk_i,
  input  logic        rst_ni,

  // TL-UL Bus Interface
  input  logic        we_i,
  input  logic [31:0] wdata_i,
  input  logic [3:0]  addr_i,
  output logic [31:0] rdata_o,

  // Interrupt output
  output logic        intr_o
);

  // Register addresses
  localparam ADDR_CTRL    = 4'h0; // control register
  localparam ADDR_COUNT   = 4'h4; // current count (read only)
  localparam ADDR_COMPARE = 4'h8; // compare value
  localparam ADDR_STATUS  = 4'hC; // status register

  // Registers
  logic [31:0] count_reg;
  logic [31:0] compare_reg;
  logic        enable;      // bit 0 of ctrl
  logic        intr_en;     // bit 1 of ctrl
  logic        intr_flag;   // interrupt pending

  // ── Register Write ──
  always_ff @(posedge clk_i or negedge rst_ni) begin
    if (!rst_ni) begin
      count_reg   <= 32'h0;
      compare_reg <= 32'hFFFF_FFFF;
      enable      <= 1'b0;
      intr_en     <= 1'b0;
      intr_flag   <= 1'b0;
    end else begin
      // Clear interrupt if status written
      if (we_i && addr_i == ADDR_STATUS) begin
        intr_flag <= 1'b0;
      end

      // Write control and compare registers
      if (we_i) begin
        case (addr_i)
          ADDR_CTRL: begin
            enable  <= wdata_i[0];
            intr_en <= wdata_i[1];
          end
          ADDR_COMPARE: compare_reg <= wdata_i;
          default: ;
        endcase
      end

      // Counter logic
      if (enable) begin
        if (count_reg == compare_reg) begin
          count_reg <= 32'h0;      // reset counter
          intr_flag <= intr_en;    // set interrupt if enabled
        end else begin
          count_reg <= count_reg + 1;
        end
      end
    end
  end

  // ── Register Read ──
  always_comb begin
    rdata_o = 32'h0;
    case (addr_i)
      ADDR_CTRL:    rdata_o = {30'h0, intr_en, enable};
      ADDR_COUNT:   rdata_o = count_reg;
      ADDR_COMPARE: rdata_o = compare_reg;
      ADDR_STATUS:  rdata_o = {31'h0, intr_flag};
      default:      rdata_o = 32'h0;
    endcase
  end

  // ── Interrupt output ──
  assign intr_o = intr_flag;

endmodule

timer_wave.vcd
$version Generated by VerilatedVcd $end
$timescale 1ps $end
 $scope module TOP $end
  $var wire 1 ( clk_i $end
  $var wire 1 ) rst_ni $end
  $var wire 1 * we_i $end
  $var wire 32 + wdata_i [31:0] $end
  $var wire 4 , addr_i [3:0] $end
  $var wire 32 - rdata_o [31:0] $end
  $var wire 1 . intr_o $end
  $scope module timer_top $end
   $var wire 1 ( clk_i $end
   $var wire 1 ) rst_ni $end
   $var wire 1 * we_i $end
   $var wire 32 + wdata_i [31:0] $end
   $var wire 4 , addr_i [3:0] $end
   $var wire 32 - rdata_o [31:0] $end
   $var wire 1 . intr_o $end
   $var wire 4 / ADDR_CTRL [3:0] $end
   $var wire 4 0 ADDR_COUNT [3:0] $end
   $var wire 4 1 ADDR_COMPARE [3:0] $end
   $var wire 4 2 ADDR_STATUS [3:0] $end
   $var wire 32 # count_reg [31:0] $end
   $var wire 32 $ compare_reg [31:0] $end
   $var wire 1 % enable $end
   $var wire 1 & intr_en $end
   $var wire 1 ' intr_flag $end
  $upscope $end
 $upscope $end
$enddefinitions $end


#0
b00000000000000000000000000000000 #
b00000000000000000000000000000000 $
0%
0&
0'
0(
0)
0*
b00000000000000000000000000000000 +
b0000 ,
b00000000000000000000000000000000 -
0.
b0000 /
b0100 0
b1000 1
b1100 2
#1
b11111111111111111111111111111111 $
1(
#2
0(
#3
1(
#4
0(
#5
1(
#6
0(
#7
1(
#8
0(
#9
1(
#10
0(
1)
#11
1(
#12
0(
1*
b00000000000000000000000000001010 +
b1000 ,
b11111111111111111111111111111111 -
#13
b00000000000000000000000000001010 $
1(
b00000000000000000000000000001010 -
#14
0(
0*
#15
1(
#16
0(
1*
b00000000000000000000000000000011 +
b0000 ,
b00000000000000000000000000000000 -
#17
1%
1&
1(
b00000000000000000000000000000011 -
#18
0(
0*
#19
b00000000000000000000000000000001 #
1(
#20
0(
#21
b00000000000000000000000000000010 #
1(
#22
0(
#23
b00000000000000000000000000000011 #
1(
#24
0(
#25
b00000000000000000000000000000100 #
1(
#26
0(
#27
b00000000000000000000000000000101 #
1(
#28
0(
#29
b00000000000000000000000000000110 #
1(
#30
0(
#31
b00000000000000000000000000000111 #
1(
#32
0(
#33
b00000000000000000000000000001000 #
1(
#34
0(
#35
b00000000000000000000000000001001 #
1(
#36
0(
#37
b00000000000000000000000000001010 #
1(
#38
0(
#39
b00000000000000000000000000000000 #
1'
1(
1.
#40
0(
b0100 ,
b00000000000000000000000000000000 -
#41
b00000000000000000000000000000001 #
1(
b00000000000000000000000000000001 -
#42
0(
#43
b00000000000000000000000000000010 #
1(
b00000000000000000000000000000010 -
#44
0(
1*
b00000000000000000000000000000001 +
b1100 ,
b00000000000000000000000000000001 -
#45
b00000000000000000000000000000011 #
0'
1(
b00000000000000000000000000000000 -
0.
#46
0(
0*
#47
b00000000000000000000000000000100 #
1(
#48
0(
1*
b00000000000000000000000000000000 +
b0000 ,
b00000000000000000000000000000011 -
#49
b00000000000000000000000000000101 #
0%
0&
1(
b00000000000000000000000000000000 -
#50
0(
0*
b0100 ,
b00000000000000000000000000000101 -
